guessenv/__init__.py
guessenv/__main__.py
guessenv/guesser.py
guessenv-0.2.dist-info/LICENSE.txt
guessenv-0.2.dist-info/METADATA
guessenv-0.2.dist-info/WHEEL
guessenv-0.2.dist-info/entry_points.txt
guessenv-0.2.dist-info/top_level.txt
guessenv-0.2.dist-info/RECORD
