Metadata-Version: 2.1
Name: guessenv
Version: 0.2
Summary: Parse Python files and look for required environment variables
Home-page: https://github.com/easypost/guessenv
Author: EasyPost OSS
Author-email: oss@easypost.com
License: ISC
Project-URL: Issue Tracker, https://github.com/easypost/guessenv/issues
Platform: UNKNOWN
Classifier: Development Status :: 3 - Alpha
Classifier: Environment :: Console
Classifier: Programming Language :: Python
Classifier: Programming Language :: Python :: 2.7
Classifier: Programming Language :: Python :: 3.5
Classifier: Programming Language :: Python :: 3.6
Classifier: Programming Language :: Python :: 3.7
Classifier: Intended Audience :: End Users/Desktop
Classifier: Operating System :: OS Independent
Classifier: License :: OSI Approved :: ISC License (ISCL)
